{
    "total_states": 14,
    "actions": ["right", "up"],
    "horizon": 8,
    "goals": [13],
    "state_transitions": [{
        "up": [[0.7, 1, -1, 0], [0.30000000000000004, 2, -1, 0]],
        "right": [[0.7, 2, -1, 0], [0.30000000000000004, 1, -1, 0]]
    }, {
        "up": [[0.7, 3, -1, 0], [0.30000000000000004, 4, -1, 0]],
        "right": [[0.7, 4, -1, 0], [0.30000000000000004, 3, -1, 0]]
    }, {
        "up": [[0.7, 4, -1, 0], [0.30000000000000004, 5, -1, 0]],
        "right": [[0.7, 5, -1, 0], [0.30000000000000004, 4, -1, 0]]
    }, {
        "up": [[0.7, 6, -1, -1], [0.30000000000000004, 7, -1, 0]],
        "right": [[0.7, 7, -1, 0], [0.30000000000000004, 6, -1, -1]]
    }, {
        "up": [[1, 7, -1, 0]],
        "right": [[1, 4, -1, 0]]
    }, {
        "up": [[1, 5, -1, 0]],
        "right": [[1, 8, -1, 0]]
    }, {
        "up": [[1, 6, -1, -1]],
        "right": [[1, 9, -1, 0]]
    }, {
        "up": [[1, 9, -1, 0]],
        "right": [[1, 7, -1, 0]]
    }, {
        "up": [[1, 10, -1, 0]],
        "right": [[1, 8, -1, 0]]
    }, {
        "up": [[1, 9, -1, 0]],
        "right": [[1, 11, -1, 0]]
    }, {
        "up": [[1, 12, -1, 0]],
        "right": [[1, 10, -1, 0]]
    }, {
        "up": [[1, 11, -1, 0]],
        "right": [[1, 13, -1, 0]]
    }, {
        "up": [[1, 13, -1, 0]],
        "right": [[1, 12, -1, 0]]
    }, {}],
    "theories": [{
        "Name": "time",
        "Type": "Cost",
        "Budget": 8,
        "Heuristic": [-6, -5, -5, -4, -4, -4, -3, -3, -3, -2, -2, -1, -1, 0],
        "Default": 0,
        "Rank": 0
    }, {
        "Name": "avoid_playgrounds",
        "Type": "Threshold",
        "Threshold": 0.95,
        "Heuristic": [-0.3333333333333333, -0.5, -0.25, -1.0, -0.3333333333333333, -0.2, -1, -0.5, -0.16666666666666666, -1.0, -0.2, -0.5, -0.25, -0.3333333333333333],
        "Default": 0,
        "Rank": 0
    }]
}